mrfix/__init__.py
mrfix/cross_platform_test_runner (1).py
mrfix/cross_platform_test_runner.py
mrfix/mrfix.py
mrfix/mrfix.zip
mrfix/mrfix_8.3.2.zip
mrfix/old_mrfix.zip
mrfix/pipeline_config.sample.json
mrfix-9.0.2.dist-info/METADATA
mrfix-9.0.2.dist-info/WHEEL
mrfix-9.0.2.dist-info/RECORD
