Metadata-Version: 2.4
Name: mrfix
Version: 9.0.2
Summary: The Mr Fix module is designed to create autotests written in Python for testing UI, API, PostgreSQL, Security, and Performance Testing.
Project-URL: homepage, https://github.com/MrFix-Autotesting-Framework
Project-URL: documentation, https://github.com/MrFix-Autotesting-Framework/docs
Project-URL: source, https://github.com/MrFix-Autotesting-Framework
Project-URL: bug-tracker, https://github.com/MrFix-Autotesting-Framework/issues
Author-email: Valerii Zhuravlev <valerii.zhuravlev.for.job@gmail.com>
License: MIT
Classifier: License :: OSI Approved :: MIT License
Classifier: Operating System :: OS Independent
Classifier: Programming Language :: Python :: 3
Requires-Python: >=3.9
Requires-Dist: beautifulsoup4
Requires-Dist: cryptography
Requires-Dist: httpx
Requires-Dist: loguru
Requires-Dist: mysql-connector-python
Requires-Dist: psycopg2-binary
Requires-Dist: pyperclip
Requires-Dist: pytest
Requires-Dist: pytest-asyncio
Requires-Dist: python-dotenv
Requires-Dist: requests
Requires-Dist: ruff
Requires-Dist: selenium
Requires-Dist: sh
Requires-Dist: tabulate
Requires-Dist: webdriver-manager
